[
	{
		"Id": 1,
		"ProductId": 1,
		"UnitPrice": 39200,
		"RecommendedRetailPrice": 49000,
		"ValidFrom": "2024-05-18T16:00:46.140177+00:00",
		"Quantity": 20,
		"Status": "InStock",
		"Barcode": " ",
		"Comment": "Good",
		"Tags": " "
	},
	{
		"Id": 2,
		"ProductId": 2,
		"UnitPrice": 60000,
		"RecommendedRetailPrice": 75000,
		"ValidFrom": "2024-05-18T16:00:46.140177+00:00",
		"Quantity": 20,
		"Status": "InStock",
		"Barcode": " ",
		"Comment": "Not Bad",
		"Tags": " "
	},
	{
		"Id": 3,
		"ProductId": 3,
		"UnitPrice": 22500,
		"RecommendedRetailPrice": 25000,
		"ValidFrom": "2024-05-18T16:00:46.140177+00:00",
		"Quantity": 20,
		"Status": "InStock",
		"Barcode": " ",
		"Comment": "Good",
		"Tags": " "
	},
	{
		"Id": 4,
		"ProductId": 3,
		"UnitPrice": 22500,
		"RecommendedRetailPrice": 25000,
		"ValidFrom": "2024-05-18T16:00:46.140177+00:00",
		"Quantity": 20,
		"Status": "InStock",
		"Barcode": " ",
		"Comment": "Not Bad",
		"Tags": " "
	},
	{
		"Id": 5,
		"ProductId": 3,
		"UnitPrice": 22500,
		"RecommendedRetailPrice": 25000,
		"ValidFrom": "2024-05-18T16:00:46.140177+00:00",
		"Quantity": 0,
		"Status": "OutOfStock",
		"Barcode": " ",
		"Comment": "Not Bad",
		"Tags": " "
	},
	{
		"Id": 6,
		"ProductId": 3,
		"UnitPrice": 22500,
		"RecommendedRetailPrice": 25000,
		"ValidFrom": "2024-05-18T16:00:46.140177+00:00",
		"Quantity": 0,
		"Status": "OutOfStock",
		"Barcode": " ",
		"Comment": "Not Bad",
		"Tags": " "
	},
	{
		"Id": 7,
		"ProductId": 3,
		"UnitPrice": 22500,
		"RecommendedRetailPrice": 25000,
		"ValidFrom": "2024-05-18T16:00:46.140177+00:00",
		"Quantity": 20,
		"Status": "InStock",
		"Barcode": " ",
		"Comment": "Good",
		"Tags": " "
	},
	{
		"Id": 8,
		"ProductId": 3,
		"UnitPrice": 22500,
		"RecommendedRetailPrice": 25000,
		"ValidFrom": "2024-05-18T16:00:46.140177+00:00",
		"Quantity": 20,
		"Status": "InStock",
		"Barcode": " ",
		"Comment": "Good",
		"Tags": " "
	},
	{
		"Id": 9,
		"ProductId": 4,
		"UnitPrice": 80100,
		"RecommendedRetailPrice": 89000,
		"ValidFrom": "2024-05-19T18:00:46.140177+00:00",
		"Quantity": 15,
		"Status": "InStock",
		"Barcode": " ",
		"Comment": "Good",
		"Tags": " "
	},
	{
		"Id": 10,
		"ProductId": 4,
		"UnitPrice": 64800,
		"RecommendedRetailPrice": 72000,
		"ValidFrom": "2024-05-19T18:00:46.140177+00:01",
		"Quantity": 27,
		"Status": "InStock",
		"Barcode": " ",
		"Comment": "Good",
		"Tags": " "
	},
	{
		"Id": 11,
		"ProductId": 4,
		"UnitPrice": 95400,
		"RecommendedRetailPrice": 106000,
		"ValidFrom": "2024-05-19T18:00:46.140177+00:02",
		"Quantity": 30,
		"Status": "InStock",
		"Barcode": " ",
		"Comment": "Not Bad",
		"Tags": " "
	},
	{
		"Id": 12,
		"ProductId": 4,
		"UnitPrice": 99900,
		"RecommendedRetailPrice": 111000,
		"ValidFrom": "2024-05-19T18:00:46.140177+00:03",
		"Quantity": 20,
		"Status": "InStock",
		"Barcode": " ",
		"Comment": "Good",
		"Tags": " "
	},
	{
		"Id": 13,
		"ProductId": 4,
		"UnitPrice": 90900,
		"RecommendedRetailPrice": 101000,
		"ValidFrom": "2024-05-19T18:00:46.140177+00:04",
		"Quantity": 0,
		"Status": "OutOfStock",
		"Barcode": " ",
		"Comment": "Not Bad",
		"Tags": " "
	},
	{
		"Id": 14,
		"ProductId": 5,
		"UnitPrice": 49500,
		"RecommendedRetailPrice": 55000,
		"ValidFrom": "2024-05-18T16:00:46.140177+00:00",
		"Quantity": 20,
		"Status": "InStock",
		"Barcode": " ",
		"Comment": "Good",
		"Tags": " "
	},
	{
		"Id": 15,
		"ProductId": 6,
		"UnitPrice": 33600,
		"RecommendedRetailPrice": 42000,
		"ValidFrom": "2024-05-18T16:00:46.140177+00:00",
		"Quantity": 15,
		"Status": "InStock",
		"Barcode": " ",
		"Comment": "Not Bad",
		"Tags": " "
	},
	{
		"Id": 16,
		"ProductId": 6,
		"UnitPrice": 33600,
		"RecommendedRetailPrice": 42000,
		"ValidFrom": "2024-05-18T16:00:46.140177+00:00",
		"Quantity": 20,
		"Status": "InStock",
		"Barcode": " ",
		"Comment": "Good",
		"Tags": " "
	},
	{
		"Id": 17,
		"ProductId": 6,
		"UnitPrice": 33600,
		"RecommendedRetailPrice": 42000,
		"ValidFrom": "2024-05-18T16:00:46.140177+00:00",
		"Quantity": 10,
		"Status": "InStock",
		"Barcode": " ",
		"Comment": "Not Bad",
		"Tags": " "
	},
	{
		"Id": 18,
		"ProductId": 6,
		"UnitPrice": 33600,
		"RecommendedRetailPrice": 42000,
		"ValidFrom": "2024-05-18T16:00:46.140177+00:00",
		"Quantity": 20,
		"Status": "InStock",
		"Barcode": " ",
		"Comment": "Good",
		"Tags": " "
	},
	{
		"Id": 19,
		"ProductId": 6,
		"UnitPrice": 33600,
		"RecommendedRetailPrice": 42000,
		"ValidFrom": "2024-05-18T16:00:46.140177+00:01",
		"Quantity": 20,
		"Status": "InStock",
		"Barcode": " ",
		"Comment": "Not Bad",
		"Tags": " "
	},
	{
		"Id": 20,
		"ProductId": 7,
		"UnitPrice": 20900,
		"RecommendedRetailPrice": 22000,
		"ValidFrom": "2024-05-18T16:00:46.140177+00:01",
		"Quantity": 20,
		"Status": "InStock",
		"Barcode": " ",
		"Comment": "Not Bad",
		"Tags": " "
	},
	{
		"Id": 21,
		"ProductId": 7,
		"UnitPrice": 20900,
		"RecommendedRetailPrice": 22000,
		"ValidFrom": "2024-05-18T16:00:46.140177+00:01",
		"Quantity": 32,
		"Status": "InStock",
		"Barcode": " ",
		"Comment": "Good",
		"Tags": " "
	},
	{
		"Id": 22,
		"ProductId": 7,
		"UnitPrice": 20900,
		"RecommendedRetailPrice": 22000,
		"ValidFrom": "2024-05-18T16:00:46.140177+00:01",
		"Quantity": 14,
		"Status": "InStock",
		"Barcode": " ",
		"Comment": "Good",
		"Tags": " "
	},
	{
		"Id": 23,
		"ProductId": 7,
		"UnitPrice": 20900,
		"RecommendedRetailPrice": 22000,
		"ValidFrom": "2024-05-18T16:00:46.140177+00:01",
		"Quantity": 26,
		"Status": "InStock",
		"Barcode": " ",
		"Comment": "Good",
		"Tags": ""
	},
	{
		"Id": 24,
		"ProductId": 7,
		"UnitPrice": 20900,
		"RecommendedRetailPrice": 22000,
		"ValidFrom": "2024-05-18T16:00:46.140177+00:01",
		"Quantity": 15,
		"Status": "InStock",
		"Barcode": " ",
		"Comment": "Good",
		"Tags": ""
	},
	{
		"Id": 25,
		"ProductId": 7,
		"UnitPrice": 20900,
		"RecommendedRetailPrice": 22000,
		"ValidFrom": "2024-05-18T16:00:46.140177+00:01",
		"Quantity": 18,
		"Status": "InStock",
		"Barcode": " ",
		"Comment": "Good",
		"Tags": ""
	},
	{
		"Id": 26,
		"ProductId": 8,
		"UnitPrice": 125300,
		"RecommendedRetailPrice": 179000,
		"ValidFrom": "2024-05-18T16:00:46.140177+00:01",
		"Quantity": 19,
		"Status": "InStock",
		"Barcode": "",
		"Comment": "Not Bad",
		"Tags": ""
	},
	{
		"Id": 27,
		"ProductId": 9,
		"UnitPrice": 97300,
		"RecommendedRetailPrice": 1390000,
		"ValidFrom": "2024-05-18T16:00:46.140177+00:01",
		"Quantity": 21,
		"Status": "InStock",
		"Barcode": "",
		"Comment": "Good",
		"Tags": ""
	},
	{
		"Id": 28,
		"ProductId": 10,
		"UnitPrice": 101500,
		"RecommendedRetailPrice": 145000,
		"ValidFrom": "2024-05-18T16:00:46.140177+00:01",
		"Quantity": 10,
		"Status": "InStock",
		"Barcode": "",
		"Comment": "Not Bad",
		"Tags": ""
	},
	{
		"Id": 29,
		"ProductId": 11,
		"UnitPrice": 95200,
		"RecommendedRetailPrice": 119000,
		"ValidFrom": "2024-05-18T16:00:46.140177+00:01",
		"Quantity": 5,
		"Status": "InStock",
		"Barcode": "",
		"Comment": "Good",
		"Tags": ""
	},
	{
		"Id": 30,
		"ProductId": 12,
		"UnitPrice": 83080,
		"RecommendedRetailPrice": 124000,
		"ValidFrom": "2024-05-18T16:00:46.140177+00:01",
		"Quantity": 15,
		"Status": "InStock",
		"Barcode": "",
		"Comment": "Good",
		"Tags": ""
	},
	{
		"Id": 31,
		"ProductId": 13,
		"UnitPrice": 97300,
		"RecommendedRetailPrice": 139000,
		"ValidFrom": "2024-05-18T16:00:46.140177+00:01",
		"Quantity": 0,
		"Status": "OutOfStock",
		"Barcode": "",
		"Comment": "Not Bad",
		"Tags": ""
	},
	{
		"Id": 32,
		"ProductId": 14,
		"UnitPrice": 62300,
		"RecommendedRetailPrice": 89000,
		"ValidFrom": "2024-05-18T16:00:46.140177+00:01",
		"Quantity": 6,
		"Status": "InStock",
		"Barcode": "",
		"Comment": "Good",
		"Tags": ""
	},
	{
		"Id": 33,
		"ProductId": 15,
		"UnitPrice": 126400,
		"RecommendedRetailPrice": 158000,
		"ValidFrom": "2024-05-18T16:00:46.140177+00:01",
		"Quantity": 8,
		"Status": "InStock",
		"Barcode": "",
		"Comment": "Not Bad",
		"Tags": ""
	},
	{
		"Id": 34,
		"ProductId": 16,
		"UnitPrice": 31350,
		"RecommendedRetailPrice": 33000,
		"ValidFrom": "2024-05-18T16:00:46.140177+00:01",
		"Quantity": 50,
		"Status": "InStock",
		"Barcode": "",
		"Comment": "Good",
		"Tags": ""
	},
	{
		"Id": 35,
		"ProductId": 16,
		"UnitPrice": 31350,
		"RecommendedRetailPrice": 33000,
		"ValidFrom": "2024-05-18T16:00:46.140177+00:01",
		"Quantity": 40,
		"Status": "InStock",
		"Barcode": "",
		"Comment": "Good",
		"Tags": ""
	},
	{
		"Id": 36,
		"ProductId": 16,
		"UnitPrice": 31350,
		"RecommendedRetailPrice": 33000,
		"ValidFrom": "2024-05-18T16:00:46.140177+00:01",
		"Quantity": 25,
		"Status": "InStock",
		"Barcode": "",
		"Comment": "Not Bad",
		"Tags": ""
	},
	{
		"Id": 37,
		"ProductId": 17,
		"UnitPrice": 5400,
		"RecommendedRetailPrice": 6000,
		"ValidFrom": "2024-05-18T16:00:46.140177+00:01",
		"Quantity": 100,
		"Status": "InStock",
		"Barcode": "",
		"Comment": "Good",
		"Tags": ""
	},
	{
		"Id": 38,
		"ProductId": 18,
		"UnitPrice": 33750,
		"RecommendedRetailPrice": 37500,
		"ValidFrom": "2024-05-18T16:00:46.140177+00:01",
		"Quantity": 50,
		"Status": "InStock",
		"Barcode": "",
		"Comment": "Not Bad",
		"Tags": ""
	},
	{
		"Id": 39,
		"ProductId": 19,
		"UnitPrice": 11700,
		"RecommendedRetailPrice": 13000,
		"ValidFrom": "2024-05-18T16:00:46.140177+00:01",
		"Quantity": 40,
		"Status": "InStock",
		"Barcode": "",
		"Comment": "Good",
		"Tags": ""
	},
	{
		"Id": 40,
		"ProductId": 20,
		"UnitPrice": 14850,
		"RecommendedRetailPrice": 16500,
		"ValidFrom": "2024-05-18T16:00:46.140177+00:01",
		"Quantity": 15,
		"Status": "InStock",
		"Barcode": "",
		"Comment": "Good",
		"Tags": ""
	}
]